passcaptcha/__init__.py
passcaptcha/audio.py
passcaptcha/base.py
passcaptcha/exceptions.py
passcaptcha/image.py
passcaptcha/passcaptcha.example.yaml
passcaptcha/predict.py
passcaptcha/proxy.py
passcaptcha/solver.py
passcaptcha/speech.py
passcaptcha/util.py
passcaptcha/data/deface.html
passcaptcha/data/jquery.js
passcaptcha/data/override.js
passcaptcha/models/yolov3.cfg
passcaptcha/models/yolov3.txt
passcaptcha-0.0.3.dist-info/LICENSE.rst
passcaptcha-0.0.3.dist-info/METADATA
passcaptcha-0.0.3.dist-info/WHEEL
passcaptcha-0.0.3.dist-info/top_level.txt
passcaptcha-0.0.3.dist-info/RECORD
