Metadata-Version: 2.1
Name: passcaptcha
Version: 0.0.3
Summary: An asynchronized Python library to automate solving ReCAPTCHA v2 by images/audio
Home-page: https://github.com/GreatWriter/PassCatpcha
Author: GreatWriter <cheung.jay@hotmail.com>, Cheung jay <cheung.jay@hotmail.com>
Author-email: cheung.jay@hotmail.com, cheung.jay@hotmail.com
License: GPL-3.0
Platform: all
Classifier: Development Status :: 5 - Production/Stable
Classifier: Intended Audience :: Developers
Classifier: Intended Audience :: Science/Research
Classifier: License :: OSI Approved :: GNU General Public License v3 (GPLv3)
Classifier: Natural Language :: English
Classifier: Operating System :: OS Independent
Classifier: Programming Language :: Python :: 3.7
Classifier: Programming Language :: JavaScript
Classifier: Topic :: Scientific/Engineering
Classifier: Topic :: Software Development :: Libraries
Classifier: Topic :: Utilities
Requires-Dist: aiobotocore (==0.9.3)
Requires-Dist: aiofiles (==0.3.2)
Requires-Dist: aiohttp (==3.3.2)
Requires-Dist: appdirs (==1.4.3)
Requires-Dist: async-generator (==1.10)
Requires-Dist: async-timeout (==3.0.0)
Requires-Dist: attrs (==19.3.0)
Requires-Dist: beautifulsoup4 (==4.8.1)
Requires-Dist: botocore (==1.10.58)
Requires-Dist: certifi (==2019.9.11)
Requires-Dist: chardet (==3.0.4)
Requires-Dist: docutils (==0.15.2)
Requires-Dist: entrypoints (==0.3)
Requires-Dist: flake8 (==3.5.0)
Requires-Dist: fuckcaptcha (==0.1.0)
Requires-Dist: idna (==2.8)
Requires-Dist: jmespath (==0.9.4)
Requires-Dist: mccabe (==0.6.1)
Requires-Dist: multidict (==4.6.1)
Requires-Dist: numpy (==1.17.4)
Requires-Dist: opencv-python (==4.1.2.30)
Requires-Dist: peewee (==3.11.2)
Requires-Dist: Pillow (==6.2.1)
Requires-Dist: pocketsphinx (==0.1.15)
Requires-Dist: psutil (==5.4.6)
Requires-Dist: pycodestyle (==2.3.1)
Requires-Dist: pydub (==0.22.1)
Requires-Dist: pyee (==6.0.0)
Requires-Dist: pyflakes (==1.6.0)
Requires-Dist: pyppeteer (==0.0.25)
Requires-Dist: pyppeteer-stealth (==1.0.0)
Requires-Dist: python-dateutil (==2.8.1)
Requires-Dist: PyYAML (==5.1.2)
Requires-Dist: requests (==2.23.0)
Requires-Dist: six (==1.14.0)
Requires-Dist: soupsieve (==1.9.5)
Requires-Dist: SpeechRecognition (==3.8.1)
Requires-Dist: tqdm (==4.39.0)
Requires-Dist: urllib3 (==1.24.3)
Requires-Dist: user-agent (==0.1.9)
Requires-Dist: websockets (==6.0)
Requires-Dist: wrapt (==1.11.2)
Requires-Dist: yarl (==1.3.0)
